{
  "project_info": {
    "project_number": "445443093627",
    "project_id": "flashchat-ef830",
    "storage_bucket": "flashchat-ef830.appspot.com"
  },
  "client": [
    {
      "client_info": {
        "mobilesdk_app_id": "1:445443093627:android:73bdda5ec7405152f71ede",
        "android_client_info": {
          "package_name": "co.DiegoDelHierro.flash_chat"
        }
      },
      "oauth_client": [
        {
          "client_id": "445443093627-u4gvq5v38t54stsrv7iurpapebptdjdt.apps.googleusercontent.com",
          "client_type": 3
        }
      ],
      "api_key": [
        {
          "current_key": "AIzaSyA9TityURZKij18kca9GHpcw55cRWc1x7I"
        }
      ],
      "services": {
        "appinvite_service": {
          "other_platform_oauth_client": [
            {
              "client_id": "445443093627-u4gvq5v38t54stsrv7iurpapebptdjdt.apps.googleusercontent.com",
              "client_type": 3
            }
          ]
        }
      }
    }
  ],
  "configuration_version": "1"
}